shieldcloudapi/__init__.py
shieldcloudapi/shieldcloudapi.py
shieldcloudapi-0.2.14.dist-info/LICENSE
shieldcloudapi-0.2.14.dist-info/METADATA
shieldcloudapi-0.2.14.dist-info/WHEEL
shieldcloudapi-0.2.14.dist-info/top_level.txt
shieldcloudapi-0.2.14.dist-info/RECORD
