Metadata-Version: 2.1
Name: shieldcloudapi
Version: 0.2.14
Summary: Intrusion Inc Shield Cloud API package
Author: John Edwards
Author-email: John Edwards <john.edwards@intrusion.com>
License: Apache License
Project-URL: Homepage, https://developer.intrusion.com
Project-URL: Bug Tracker, https://github.com/Jarvis-Int-Inc/shieldpython/issues
Classifier: Programming Language :: Python :: 3
Classifier: License :: OSI Approved :: Apache Software License
Classifier: Operating System :: OS Independent
Requires-Python: >=3.8
License-File: LICENSE
